[
  {
    "symbol": "BIL",
    "date": "2025-10-17",
    "price": 7.5,
    "change": -0.1,
    "changePercent": -1.3157894736842106,
    "volume": 3943463,
    "high": 7.6,
    "low": 7.4,
    "open": 7.5,
    "close": 7.6
  },
  {
    "symbol": "CINS",
    "date": "2025-10-17",
    "price": 1875,
    "change": 5,
    "changePercent": 0.26737967914438504,
    "volume": 2040,
    "high": 1899.5,
    "low": 1850,
    "open": 1850,
    "close": 1870
  },
  {
    "symbol": "CINS",
    "date": "2025-10-17",
    "price": 3096.75,
    "change": 0,
    "changePercent": 0,
    "volume": 21,
    "high": 3150,
    "low": 3100,
    "open": 3100,
    "close": 3096.75
  },
  {
    "symbol": "COMB",
    "date": "2025-10-17",
    "price": 206.5,
    "change": 1.5,
    "changePercent": 0.7317073170731707,
    "volume": 378496,
    "high": 206.75,
    "low": 204,
    "open": 205,
    "close": 205
  },
  {
    "symbol": "COMB",
    "date": "2025-10-17",
    "price": 188.75,
    "change": 0.5,
    "changePercent": 0.2656042496679947,
    "volume": 31628,
    "high": 189.5,
    "low": 187.25,
    "open": 188.25,
    "close": 188.25
  },
  {
    "symbol": "DIAL",
    "date": "2025-10-17",
    "price": 29,
    "change": -0.1,
    "changePercent": -0.3436426116838488,
    "volume": 1910586,
    "high": 29.2,
    "low": 27.5,
    "open": 29.2,
    "close": 29.1
  },
  {
    "symbol": "HNB",
    "date": "2025-10-17",
    "price": 314,
    "change": -0.25,
    "changePercent": -0.07955449482895784,
    "volume": 519189,
    "high": 315,
    "low": 313.75,
    "open": 314.5,
    "close": 314.25
  },
  {
    "symbol": "HNB",
    "date": "2025-10-17",
    "price": 396,
    "change": 1.5,
    "changePercent": 0.38022813688212925,
    "volume": 210022,
    "high": 398,
    "low": 394.5,
    "open": 397,
    "close": 394.5
  },
  {
    "symbol": "JKH",
    "date": "2025-10-17",
    "price": 21.8,
    "change": 0.3,
    "changePercent": 1.3953488372093024,
    "volume": 5569387,
    "high": 21.8,
    "low": 21.6,
    "open": 21.6,
    "close": 21.5
  },
  {
    "symbol": "LFIN",
    "date": "2025-10-17",
    "price": 170.5,
    "change": 2.25,
    "changePercent": 1.337295690936107,
    "volume": 250404,
    "high": 172,
    "low": 170,
    "open": 170,
    "close": 168.25
  },
  {
    "symbol": "LOLC",
    "date": "2025-10-17",
    "price": 560.5,
    "change": -7,
    "changePercent": -1.2334801762114538,
    "volume": 45673,
    "high": 580,
    "low": 560,
    "open": 569.75,
    "close": 567.5
  },
  {
    "symbol": "NTB",
    "date": "2025-10-17",
    "price": 400,
    "change": 0,
    "changePercent": 0,
    "volume": 93,
    "high": 400,
    "low": 390,
    "open": 390,
    "close": 400
  },
  {
    "symbol": "NTB",
    "date": "2025-10-17",
    "price": 299,
    "change": -0.75,
    "changePercent": -0.25020850708924103,
    "volume": 29599,
    "high": 300,
    "low": 298.75,
    "open": 300,
    "close": 299.75
  },
  {
    "symbol": "SAMP",
    "date": "2025-10-17",
    "price": 148.5,
    "change": 0.75,
    "changePercent": 0.5076142131979695,
    "volume": 495649,
    "high": 149.25,
    "low": 147.75,
    "open": 147.75,
    "close": 147.75
  },
  {
    "symbol": "VONE",
    "date": "2025-10-17",
    "price": 99.3,
    "change": 1.6,
    "changePercent": 1.6376663254861823,
    "volume": 314216,
    "high": 99.9,
    "low": 97.7,
    "open": 98,
    "close": 97.7
  }
]